LICENSE.txt
MANIFEST.in
README.md
README.rst
requirements.txt
setup.py
pug/__init__.py
pug/ann/__init__.py
pug/ann/example.py
pug/ann/net.py
pug/ann/package_info.py
pug/ann/test_maze.py
pug/ann/tests.py
pug/ann/util.py
pug/ann/data/__init__.py
pug/ann/data/__init__.pyc
pug/ann/data/weather.py
pug/ann/data/weather.pyc
pug/ann/data/cache/LICENSE
pug/ann/data/cache/README
pug/ann/data/cache/airport.locations.json
pug/ann/data/cache/daily-1W1-2011-2015.csv
pug/ann/data/cache/daily-1W1-2012-2014.csv
pug/ann/data/cache/daily-1W1-2013-2015.csv
pug/ann/data/cache/daily-1W1-2014-2015.csv
pug/ann/data/cache/daily-KMCC-2013-2013.csv
pug/ann/data/cache/daily-KPDX-2013-2015.csv
pug/ann/data/cache/daily-KSFO-2010-2013.csv
pug/ann/data/cache/daily-KSFO-2010-2014.csv
pug/ann/data/cache/daily-KSFO-2013-2014.csv
pug/ann/data/cache/daily-KSFO-2014-2014.csv
pug/ann/data/cache/daily-KSFO-2014-2015.csv
pug_ann.egg-info/PKG-INFO
pug_ann.egg-info/SOURCES.txt
pug_ann.egg-info/dependency_links.txt
pug_ann.egg-info/namespace_packages.txt
pug_ann.egg-info/requires.txt
pug_ann.egg-info/top_level.txt