Metadata-Version: 1.1
Name: pug-ann
Version: 0.0.21
Summary: # pug-ann 
Home-page: UNKNOWN
Author: Hobson <hobson@totalgood.com>
Author-email: hobson@totalgood.com
License: UNKNOWN
Download-URL: https://github.com/hobson/pug-ann/tarball/master
Keywords: artificial neural network,neural network,pybrain,agent,bot,ai,crawl,data,science,data science,math,machine-learning,statistics,database
Platform: UNKNOWN
Classifier: Programming Language :: Python
Classifier: Programming Language :: Python :: 2.7
Classifier: Development Status :: 3 - Alpha
Classifier: Environment :: Other Environment
Classifier: Environment :: Console
Classifier: Intended Audience :: Developers
Classifier: License :: OSI Approved :: MIT License
Classifier: Operating System :: OS Independent
Classifier: Topic :: Software Development :: Libraries :: Python Modules
Classifier: Topic :: Scientific/Engineering :: Artificial Intelligence
Classifier: Topic :: Scientific/Engineering :: Mathematics
